random_tools/__init__.py
random_tools/css_color.py
random_tools/signal.py
random_tools-0.2.0.dist-info/WHEEL
random_tools-0.2.0.dist-info/METADATA
random_tools-0.2.0.dist-info/RECORD
