Metadata-Version: 2.1
Name: random-tools
Version: 0.2.0
Summary: 
Home-page: https://github.com/rallesiardo/random_tools
Author: Robin Allesiardo
Author-email: robin.allesiardo@gmail.com
Requires-Python: >=3.7,<4.0
Classifier: Programming Language :: Python :: 3
Classifier: Programming Language :: Python :: 3.7
Classifier: Programming Language :: Python :: 3.8
Classifier: Programming Language :: Python :: 3.9
Requires-Dist: matplotlib (>=3.4.2,<4.0.0)
Project-URL: Repository, https://github.com/rallesiardo/random_tools
